[{"question":" What is an abstract class?","options":[{"text":"An abstract class is the name for any class from which you can instantiate an object.","correct":false},{"text":"Abstract classes must be redefined any time an object is instantiated from them.","correct":false},{"text":"Abstract classes must inherit from concrete classes.","correct":false},{"text":"An abstract class exists only so that other \"concrete\" classes can inherit from the abstract class.","correct":true}],"illustrator":""},{"question":" What happens when you use the build-in function `any()` on a list?","options":[{"text":"The `any()` function will randomly return any item from the list.","correct":false},{"text":"The `any()` function returns True if any item in the list evaluates to True. Otherwise, it returns False.","correct":true},{"text":"The `any()` function takes as arguments the list to check inside, and the item to check for. If \"any\" of the items in the list match the item to check for, the function returns True.","correct":false},{"text":"The `any()` function returns a Boolean value that answers the question \"Are there any items in this list?\"","correct":false}],"illustrator":"```python\nif any([True, False, False, False]) == True:\n    print('Yes, there is True')\n>>> 'Yes, there is True'\n```"},{"question":" What data structure does a binary tree degenerate to if it isn't balanced properly?","options":[{"text":"linked list","correct":true},{"text":"queue","correct":false},{"text":"set","correct":false},{"text":"OrderedDict","correct":false}],"illustrator":""},{"question":" What statement about static methods is true?","options":[{"text":"Static methods are called static because they always return `None`.","correct":false},{"text":"Static methods can be bound to either a class or an instance of a class.","correct":false},{"text":"Static methods serve mostly as utility methods or helper methods, since they can't access or modify a class's state.","correct":true},{"text":"Static methods can access and modify the state of a class or an instance of a class.","correct":false}],"illustrator":""},{"question":" What are attributes?","options":[{"text":"Attributes are long-form version of an `if/else` statement, used when testing for equality between objects.","correct":false},{"text":"Attributes are a way to hold data or describe a state for a class or an instance of a class.","correct":true},{"text":"Attributes are strings that describe characteristics of a class.","correct":false},{"text":"Function arguments are called \"attributes\" in the context of class methods and instance methods.","correct":false}],"illustrator":""},{"question":" What is the term to describe this code?","options":[{"text":"`tuple assignment`","correct":false},{"text":"`tuple unpacking`","correct":true},{"text":"`tuple matching`","correct":false},{"text":"`tuple duplication`","correct":false}],"illustrator":""},{"question":" What built-in list method would you use to remove items from a list?","options":[{"text":"`.delete()` method","correct":false},{"text":"`pop(my_list)`","correct":false},{"text":"`del(my_list)`","correct":false},{"text":"`.pop()` method","correct":true}],"illustrator":"```python\nmy_list = [1,2,3]\nmy_list.pop(0)\nmy_list\n>>>[2,3]\n```"},{"question":" What is one of the most common use of Python's sys library?","options":[{"text":"to capture command-line arguments given at a file's runtime","correct":true},{"text":"to connect various systems, such as connecting a web front end, an API service, a database, and a mobile app","correct":false},{"text":"to take a snapshot of all the packages and libraries in your virtual environment","correct":false},{"text":"to scan the health of your Python ecosystem while inside a virtual environment","correct":false}],"illustrator":""},{"question":" What is the runtime of accessing a value in a dictionary by using its key?","options":[{"text":"O(n), also called linear time.","correct":false},{"text":"O(log n), also called logarithmic time.","correct":false},{"text":"O(n^2), also called quadratic time.","correct":false},{"text":"O(1), also called constant time.","correct":true}],"illustrator":""},{"question":". What is the correct syntax for defining a class called Game, if it inherits from a parent class called LogicGame?","options":[{"text":"`class Game(LogicGame): pass`","correct":true},{"text":"`def Game(LogicGame): pass`","correct":false},{"text":"`def Game.LogicGame(): pass`","correct":false},{"text":"`class Game.LogicGame(): pass`","correct":false}],"illustrator":""},{"question":". What is the correct way to write a doctest?","options":[{"text":"A","correct":false},{"text":"B","correct":true},{"text":"C","correct":false},{"text":"D","correct":false}],"illustrator":"```python\ndef sum(a, b):\n    ###\n    >>> sum(4, 3)\n    7\n    >>> sum(-4, 5)\n    1\n    ###\n    return a + b\n```"},{"question":". What built-in Python data type is commonly used to represent a stack?","options":[{"text":"`set`","correct":false},{"text":"`list`","correct":true},{"text":"`None`","correct":false},{"text":"`dictionary`","correct":false},{"text":"`You can only build a stack from scratch.`","correct":false}],"illustrator":""},{"question":". What would this expression return?","options":[{"text":"`[('Freshman', 2019), ('Sophomore', 2020), ('Junior', 2021), ('Senior', 2022)]`","correct":false},{"text":"`[(2019, 2020, 2021, 2022), ('Freshman', 'Sophomore', 'Junior', 'Senior')]`","correct":false},{"text":"`[('Freshman', 'Sophomore', 'Junior', 'Senior'), (2019, 2020, 2021, 2022)]`","correct":false},{"text":"`[(2019, 'Freshman'), (2020, 'Sophomore'), (2021, 'Junior'), (2022, 'Senior')]`","correct":true}],"illustrator":"```python\ncollege_years = ['Freshman', 'Sophomore', 'Junior', 'Senior']\nreturn list(enumerate(college_years, 2019))\n```"},{"question":". What is the purpose of the \"self\" keyword when defining or calling instance methods?","options":[{"text":"`self` means that no other arguments are required to be passed into the method.","correct":false},{"text":"There is no real purpose for the `self` method; it's just historic computer science jargon that Python keeps to stay consistent with other programming languages.","correct":false},{"text":"`self` refers to the instance whose method was called.","correct":true},{"text":"`self` refers to the class that was inherited from to create the object using `self`.","correct":false}],"illustrator":"```python\nclass my_secrets:\n    def __init__(self, password):\n        self.password = password\n        pass\ninstance = my_secrets('1234')\ninstance.password\n>>>'1234'\n```"},{"question":". Which of these is NOT a characteristic of namedtuples?","options":[{"text":"You can assign a name to each of the `namedtuple` members and refer to them that way, similarly to how you would access keys in `dictionary`.","correct":false},{"text":"Each member of a namedtuple object can be indexed to directly, just like in a regular `tuple`.","correct":false},{"text":"`namedtuples` are just as memory efficient as regular `tuples`.","correct":false},{"text":"No import is needed to use `namedtuples` because they are available in the standard library.","correct":true}],"illustrator":""},{"question":". What is an instance method?","options":[{"text":"Instance methods can modify the state of an instance or the state of its parent class.","correct":true},{"text":"Instance methods hold data related to the instance.","correct":false},{"text":"An instance method is any class method that doesn't take any arguments.","correct":false},{"text":"An instance method is a regular function that belongs to a class, but it must return `None`.","correct":false}],"illustrator":""},{"question":". Which statement does NOT describe the object-oriented programming concept of encapsulation?","options":[{"text":"It protects the data from outside interference.","correct":false},{"text":"A parent class is encapsulated and no data from the parent class passes on to the child class.","correct":false},{"text":"It keeps data and the methods that can manipulate that data in one place.","correct":false},{"text":"It only allows the data to be changed by methods.","correct":true}],"illustrator":""},{"question":". What is the purpose of an if/else statement?","options":[{"text":"It tells the computer which chunk of code to run if the instructions you coded are incorrect.","correct":false},{"text":"It runs one chunk of code if all the imports were successful, and another chunk of code if the imports were not successful.","correct":false},{"text":"It executes one chunk of code if a condition is true, but a different chunk of code if the condition is false.","correct":true},{"text":"It tells the computer which chunk of code to run if the is enough memory to handle it, and which chunk of code to run if there is not enough memory to handle it.","correct":false}],"illustrator":""},{"question":". What built-in Python data type is best suited for implementing a queue?","options":[{"text":"dictionary","correct":false},{"text":"set","correct":false},{"text":"None. You can only build a queue from scratch.","correct":false},{"text":"list","correct":true}],"illustrator":""},{"question":". What is the correct syntax for instantiating a new object of the type Game?","options":[{"text":"`my_game = class.Game()`","correct":false},{"text":"`my_game = class(Game)`","correct":false},{"text":"`my_game = Game()`","correct":true},{"text":"`my_game = Game.create()`","correct":false}],"illustrator":""},{"question":". What does the built-in `map()` function do?","options":[{"text":"It creates a path from multiple values in an iterable to a single value.","correct":false},{"text":"It applies a function to each item in an iterable and returns the value of that function.","correct":true},{"text":"It converts a complex value type into simpler value types.","correct":false},{"text":"It creates a mapping between two different elements of different iterables.","correct":false}],"illustrator":"```python\nimport math\nradius = [1,2,3]\narea = list(map(lambda x: round(math.pi*(x**2), 2), radius))\narea\n>>> [3.14, 12.57, 28.27]\n```"},{"question":". If you don't explicitly return a value from a function, what happens?","options":[{"text":"The function will return a RuntimeError if you don't return a value.","correct":false},{"text":"If the return keyword is absent, the function will return `None`.","correct":true},{"text":"If the return keyword is absent, the function will return `True`.","correct":false},{"text":"The function will enter an infinite loop because it won't know when to stop executing its code.","correct":false}],"illustrator":""},{"question":". What is the purpose of the `pass` statement in Python?","options":[{"text":"It is used to skip the `yield` statement of a generator and return a value of None.","correct":false},{"text":"It is a null operation used mainly as a placeholder in functions, classes, etc.","correct":true},{"text":"It is used to pass control from one statement block to another.","correct":false},{"text":"It is used to skip the rest of a `while` or `for loop` and return to the start of the loop.","correct":false}],"illustrator":""},{"question":". What is the term used to describe items that may be passed into a function?","options":[{"text":"arguments","correct":true},{"text":"paradigms","correct":false},{"text":"attributes","correct":false},{"text":"decorators","correct":false}],"illustrator":""},{"question":". Which collection type is used to associate values with unique keys?","options":[{"text":"`slot`","correct":false},{"text":"`dictionary`","correct":true},{"text":"`queue`","correct":false},{"text":"`sorted list`","correct":false}],"illustrator":""},{"question":". When does a for loop stop iterating?","options":[{"text":"when it encounters an infinite loop","correct":false},{"text":"when it encounters an if/else statement that contains a break keyword","correct":false},{"text":"when it has assessed each item in the iterable it is working on or a break keyword is encountered","correct":true},{"text":"when the runtime for the loop exceeds O(n^2)","correct":false}],"illustrator":""},{"question":". Assuming the node is in a singly linked list, what is the runtime complexity of searching for a specific node within a singly linked list?","options":[{"text":"The runtime is O(n) because in the worst case, the node you are searching for is the last node, and every node in the linked list must be visited.","correct":true},{"text":"The runtime is O(nk), with n representing the number of nodes and k representing the amount of time it takes to access each node in memory.","correct":false},{"text":"The runtime cannot be determined unless you know how many nodes are in the singly linked list.","correct":false},{"text":"The runtime is O(1) because you can index directly to a node in a singly linked list.","correct":false}],"illustrator":""},{"question":". Given the following three list, how would you create a new list that matches the desired output printed below?","options":[{"text":"<br>","correct":false},{"text":"<br>","correct":true},{"text":"<br>","correct":false},{"text":" <br>","correct":false}],"illustrator":"```python\ni = 0\noutput = []\nfor fruit in fruits:\n    for qty in quantities:\n        for price in prices:\n            output.append((fruit, qty, price))\n    i += 1\nreturn output\n```"},{"question":". What happens when you use the built-in function all() on a list?","options":[{"text":"The `all()` function returns a Boolean value that answers the question \"Are all the items in this list the same?","correct":false},{"text":"The `all()` function returns True if all the items in the list can be converted to strings. Otherwise, it returns False.","correct":false},{"text":"The `all()` function will return all the values in the list.","correct":false},{"text":"The `all()` function returns True if all items in the list evaluate to True. Otherwise, it returns False.","correct":true}],"illustrator":"```python\ntest = [True,False,False,False]\nif all(test) is True:\n    print('Yeah all are True')\nelse:\n    print('There is an imposter')\n>>> 'There is an imposter'\n```"},{"question":". What is the correct syntax for calling an instance method on a class named Game?","options":[{"text":"<br>","correct":true},{"text":"<br>","correct":false},{"text":"<br>","correct":false},{"text":"<br>","correct":false}],"illustrator":"```python\n>>> dice = Game(self)\n>>> dice.roll()\n```"},{"question":". What is the algorithmic paradigm of quick sort?","options":[{"text":"backtracking","correct":false},{"text":"dynamic programming","correct":false},{"text":"decrease and conquer","correct":false},{"text":"divide and conquer","correct":true}],"illustrator":""},{"question":". What is runtime complexity of the list's built-in `.append()` method?","options":[{"text":"O(1), also called constant time","correct":true},{"text":"O(log n), also called logarithmic time","correct":false},{"text":"O(n^2), also called quadratic time","correct":false},{"text":"O(n), also called linear time","correct":false}],"illustrator":""},{"question":". What is key difference between a `set` and a `list`?","options":[{"text":"A set is an ordered collection unique items. A list is an unordered collection of non-unique items.","correct":false},{"text":"Elements can be retrieved from a list but they cannot be retrieved from a set.","correct":false},{"text":"A set is an ordered collection of non-unique items. A list is an unordered collection of unique items.","correct":false},{"text":"A set is an unordered collection unique items. A list is an ordered collection of non-unique items.","correct":true}],"illustrator":""},{"question":". What is the definition of abstraction as applied to object-oriented Python?","options":[{"text":"Abstraction means that a different style of code can be used, since many details are already known to the program behind the scenes.","correct":false},{"text":"Abstraction means the implementation is hidden from the user, and only the relevant data or information is shown.","correct":true},{"text":"Abstraction means that the data and the functionality of a class are combined into one entity.","correct":false},{"text":"Abstraction means that a class can inherit from more than one parent class.","correct":false}],"illustrator":""},{"question":". What does this function print?","options":[{"text":"<br>","correct":true},{"text":"<br>","correct":false},{"text":"<br>","correct":false},{"text":"<br>","correct":false}],"illustrator":"```python\na 1 2 3\nb 1 2 3\nc 1 2 3\n```"},{"question":". Pick correct representation of doctest for function in Python.","options":[{"text":"<br>","correct":false},{"text":"<br>","correct":false},{"text":"<br>","correct":true},{"text":"<br>","correct":false}],"illustrator":"```python\ndef sum(a, b):\n    '''\n    a = 1\n    b = 2\n    sum(a, b) = 3\n    '''\n    return a + b\n```"},{"question":". Suppose a Game class inherits from two parent classes: BoardGame and LogicGame. Which statement is true about the methods of an object instantiated from the Game class?","options":[{"text":"When instantiating an object, the object doesn't inherit any of the parent class's methods.","correct":false},{"text":"When instantiating an object, the object will inherit the methods of whichever parent class has more methods.","correct":false},{"text":"When instantiating an object, the programmer must specify which parent class to inherit methods from.","correct":false},{"text":"An instance of the Game class will inherit whatever methods the BoardGame and LogicGame classes have.","correct":true}],"illustrator":""},{"question":". What does calling namedtuple on a collection type return?","options":[{"text":"a generic object class with iterable parameter fields","correct":false},{"text":"a generic object class with non-iterable named fields","correct":false},{"text":"a tuple subclass with non-iterable parameter fields","correct":false},{"text":"a tuple subclass with iterable named fields","correct":true}],"illustrator":"```python\nimport math\nradius = [1,2,3]\narea = list(map(lambda x: round(math.pi*(x**2), 2), radius))\narea\n>>> [3.14, 12.57, 28.27]\n```"},{"question":". What symbol(s) do you use to assess equality between two elements?","options":[{"text":"`&&`","correct":false},{"text":"`=`","correct":false},{"text":"`==`","correct":true},{"text":"`||`","correct":false}],"illustrator":""},{"question":". Review the code below. What is the correct syntax for changing the price to 1.5?","options":[{"text":"`fruit_info ['price'] = 1.5`","correct":true},{"text":"`my_list [3.5] = 1.5`","correct":false},{"text":"`1.5 = fruit_info ['price]`","correct":false},{"text":"`my_list['price'] == 1.5`","correct":false}],"illustrator":"```python\nfruit_info = {\n  'fruit': 'apple',\n  'count': 2,\n  'price': 3.5\n}\n```"},{"question":". What value would be returned by this check for equality?","options":[{"text":"`yes`","correct":false},{"text":"`False`","correct":false},{"text":"`True`","correct":true},{"text":"`None`","correct":false}],"illustrator":""},{"question":". What does a class's `__init__()` method do?","options":[{"text":"It makes classes aware of each other if more than one class is defined in a single code file.","correct":false},{"text":"It is included to preserve backwards compatibility from Python 3 to Python 2, but no longer needs to be used in Python 3.","correct":false},{"text":"It is a method that acts as a constructor and is called automatically whenever a new object is created from a class. It sets the initial state of a new object.","correct":true},{"text":"It initializes any imports you may have included at the top of your file.","correct":false}],"illustrator":"```python\nclass test:\n    def __init__(self):\n        print('I came here without your permission lol')\n        pass\nt1 = test()\n>>> 'I came here without your permission lol'\n```"},{"question":". What is meant by the phrase \"space complexity\"?","options":[{"text":"`How many microprocessors it would take to run your code in less than one second`","correct":false},{"text":"`How many lines of code are in your code file`","correct":false},{"text":"`The amount of space taken up in memory as a function of the input size`","correct":true},{"text":"`How many copies of the code file could fit in 1 GB of memory`","correct":false}],"illustrator":""},{"question":". What is the correct syntax for creating a variable that is bound to a dictionary?","options":[{"text":"`fruit_info = {'fruit': 'apple', 'count': 2, 'price': 3.5}`","correct":true},{"text":"`fruit_info =('fruit': 'apple', 'count': 2,'price': 3.5 ).dict()`","correct":false},{"text":"`fruit_info = ['fruit': 'apple', 'count': 2,'price': 3.5 ].dict()`","correct":false},{"text":"`fruit_info = to_dict('fruit': 'apple', 'count': 2, 'price': 3.5)`","correct":false}],"illustrator":""},{"question":". What is the proper way to write a list comprehension that represents all the keys in this dictionary?","options":[{"text":"`fruit_names = [x in fruits.keys() for x]`","correct":false},{"text":"`fruit_names = for x in fruits.keys() *`","correct":false},{"text":"`fruit_names = [x for x in fruits.keys()]`","correct":true},{"text":"`fruit_names = x for x in fruits.keys()`","correct":false}],"illustrator":""},{"question":". What is the purpose of the `self` keyword when defining or calling methods on an instance of an object?","options":[{"text":"`self` refers to the class that was inherited from to create the object using `self`.","correct":false},{"text":"There is no real purpose for the `self` method. It's just legacy computer science jargon that Python keeps to stay consistent with other programming languages.","correct":false},{"text":"`self` means that no other arguments are required to be passed into the method.","correct":false},{"text":"`self` refers to the instance whose method was called.","correct":true}],"illustrator":""},{"question":". What statement about the class methods is true?","options":[{"text":"A class method is a regular function that belongs to a class, but it must return None.","correct":false},{"text":"A class method can modify the state of the class, but they can't directly modify the state of an instance that inherits from that class.","correct":true},{"text":"A class method is similar to a regular function, but a class method doesn't take any arguments.","correct":false},{"text":"A class method hold all of the data for a particular class.","correct":false}],"illustrator":""},{"question":". What does it mean for a function to have linear runtime?","options":[{"text":"You did not use very many advanced computer programming concepts in your code.","correct":false},{"text":"The difficulty level your code is written at is not that high.","correct":false},{"text":"It will take your program less than half a second to run.","correct":false},{"text":"The amount of time it takes the function to complete grows linearly as the input size increases.","correct":true}],"illustrator":""},{"question":". What is the proper way to define a function?","options":[{"text":"`def getMaxNum(list_of_nums): # body of function goes here`","correct":false},{"text":"`func get_max_num(list_of_nums): # body of function goes here`","correct":false},{"text":"`func getMaxNum(list_of_nums): # body of function goes here`","correct":false},{"text":"`def get_max_num(list_of_nums): # body of function goes here`","correct":true}],"illustrator":""},{"question":". According to the PEP 8 coding style guidelines, how should constant values be named in Python?","options":[{"text":"in camel case without using underscores to separate words -- e.g. `maxValue = 255`","correct":false},{"text":"in lowercase with underscores to separate words -- e.g. `max_value = 255`","correct":false},{"text":"in all caps with underscores separating words -- e.g. `MAX_VALUE = 255`","correct":true},{"text":"in mixed case without using underscores to separate words -- e.g. `MaxValue = 255`","correct":false}],"illustrator":""},{"question":". Describe the functionality of a deque.","options":[{"text":"A deque adds items to one side and remove items from the other side.","correct":false},{"text":"A deque adds items to either or both sides, but only removes items from the top.","correct":false},{"text":"A deque adds items at either or both ends, and remove items at either or both ends.","correct":true},{"text":"A deque adds items only to the top, but remove from either or both sides.","correct":false}],"illustrator":""},{"question":". What is the correct syntax for creating a variable that is bound to a set?","options":[{"text":"`my_set = {0, 'apple', 3.5}`","correct":true},{"text":"`my_set = to_set(0, 'apple', 3.5)`","correct":false},{"text":"`my_set = (0, 'apple', 3.5).to_set()`","correct":false},{"text":"`my_set = (0, 'apple', 3.5).set()`","correct":false}],"illustrator":""},{"question":". What is the correct syntax for defining an `__init__()` method that takes no parameters?","options":[{"text":"<br>","correct":false},{"text":"<br>","correct":false},{"text":"<br>","correct":false},{"text":"<br>","correct":true}],"illustrator":"```python\ndef __init__(self):\n    pass\n```"},{"question":". Which of the following is TRUE About how numeric data would be organised in a binary Search tree?","options":[{"text":"For any given Node in a binary Search Tree, the child node to the left is less than the value of the given node and the child node to its right is greater than the given node.","correct":true},{"text":"Binary Search Tree cannot be used to organize and search through numeric data, given the complication that arise with very deep trees.","correct":false},{"text":"The top node of the binary search tree would be an arbitrary number. All the nodes to the left of the top node need to be less than the top node's number, but they don't need to ordered in any particular way.","correct":false},{"text":"The smallest numeric value would go in the top most node. The next highest number would go in its left child node, the the next highest number after that would go in its right child node. This pattern would continue until all numeric values were in their own node.","correct":false}],"illustrator":""},{"question":". Why would you use a decorator?","options":[{"text":"A decorator is similar to a class and should be used if you are doing functional programming instead of object oriented programming.","correct":false},{"text":"A decorator is a visual indicator to someone reading your code that a portion of your code is critical and should not be changed.","correct":false},{"text":"You use the decorator to alter the functionality of a function without having to modify the functions code.","correct":true},{"text":"An import statement is preceded by a decorator, python knows to import the most recent version of whatever package or library is being imported.","correct":false}],"illustrator":""},{"question":". When would you use a for loop?","options":[{"text":"Only in some situations, as loops are used only for certain type of programming.","correct":false},{"text":"When you need to check every element in an iterable of known length.","correct":true},{"text":"When you want to minimize the use of strings in your code.","correct":false},{"text":"When you want to run code in one file for a function in another file.","correct":false}],"illustrator":""},{"question":". What is the most self-descriptive way to define a function that calculates sales tax on a purchase?","options":[{"text":"<br>","correct":false},{"text":"<br>","correct":false},{"text":"<br>","correct":false},{"text":"<br>","correct":true}],"illustrator":"```python\ndef calculate_sales_tax(subtotal):\n    pass\n```"},{"question":". What would happen if you did not alter the state of the element that an algorithm is operating on recursively?","options":[{"text":"You do not have to alter the state of the element the algorithm is recursing on.","correct":false},{"text":"You would eventually get a KeyError when the recursive portion of the code ran out of items to recurse on.","correct":false},{"text":"You would get a RuntimeError: maximum recursion depth exceeded.","correct":true},{"text":"The function using recursion would return None.","correct":false}],"illustrator":""},{"question":". What is the runtime complexity of searching for an item in a binary search tree?","options":[{"text":"The runtime for searching in a binary search tree is O(1) because each node acts as a key, similar to a dictionary.","correct":false},{"text":"The runtime for searching in a binary search tree is O(n!) because every node must be compared to every other node.","correct":false},{"text":"The runtime for searching in a binary search tree is generally O(h), where h is the height of the tree.","correct":true},{"text":"The runtime for searching in a binary search tree is O(n) because every node in the tree must be visited.","correct":false}],"illustrator":""},{"question":". Why would you use `mixin`?","options":[{"text":"You use a `mixin` to force a function to accept an argument at runtime even if the argument wasn't included in the function's definition.","correct":false},{"text":"You use a `mixin` to allow a decorator to accept keyword arguments.","correct":false},{"text":"You use a `mixin` to make sure that a class's attributes and methods don't interfere with global variables and functions.","correct":false},{"text":"If you have many classes that all need to have the same functionality, you'd use a `mixin` to define that functionality.","correct":true}],"illustrator":""},{"question":". What is the runtime complexity of adding an item to a stack and removing an item from a stack?","options":[{"text":"Add items to a stack in O(1) time and remove items from a stack on O(n) time.","correct":false},{"text":"Add items to a stack in O(1) time and remove items from a stack in O(1) time.","correct":true},{"text":"Add items to a stack in O(n) time and remove items from a stack on O(1) time.","correct":false},{"text":"Add items to a stack in O(n) time and remove items from a stack on O(n) time.","correct":false}],"illustrator":""},{"question":". Which statement accurately describes how items are added to and removed from a stack?","options":[{"text":"a stacks adds items to one side and removes items from the other side.","correct":false},{"text":"a stacks adds items to the top and removes items from the top.","correct":true},{"text":"a stacks adds items to the top and removes items from anywhere in the stack.","correct":false},{"text":"a stacks adds items to either end and removes items from either end.","correct":false}],"illustrator":""},{"question":". What is a base case in a recursive function?","options":[{"text":"A base case is the condition that allows the algorithm to stop recursing. It is usually a problem that is small enough to solve directly.","correct":true},{"text":"The base case is summary of the overall problem that needs to be solved.","correct":false},{"text":"The base case is passed in as an argument to a function whose body makes use of recursion.","correct":false},{"text":"The base case is similar to a base class, in that it can be inherited by another object.","correct":false}],"illustrator":""},{"question":". Why is it considered good practice to open a file from within a Python script by using the `with` keyword?","options":[{"text":"The `with` keyword lets you choose which application to open the file in.","correct":false},{"text":"The `with` keyword acts like a `for` loop, and lets you access each line in the file one by one.","correct":false},{"text":"There is no benefit to using the `with` keyword for opening a file in Python.","correct":false},{"text":"When you open a file using the `with` keyword in Python, Python will make sure the file gets closed, even if an exception or error is thrown.","correct":true}],"illustrator":""},{"question":". Why would you use a virtual environment?","options":[{"text":"Virtual environments create a \"bubble\" around your project so that any libraries or packages you install within it don't affect your entire machine.","correct":true},{"text":"Teams with remote employees use virtual environments so they can share code, do code reviews, and collaborate remotely.","correct":false},{"text":"Virtual environments were common in Python 2 because they augmented missing features in the language. Virtual environments are not necessary in Python 3 due to advancements in the language.","correct":false},{"text":"Virtual environments are tied to your GitHub or Bitbucket account, allowing you to access any of your repos virtually from any machine.","correct":false}],"illustrator":""},{"question":". What is the correct way to run all the doctests in a given file from the command line?","options":[{"text":"`python3 -m doctest <_filename_>`","correct":true},{"text":"`python3 <_filename_>`","correct":false},{"text":"`python3 <_filename_> rundoctests`","correct":false},{"text":"`python3 doctest`","correct":false}],"illustrator":""},{"question":". What is a lambda function ?","options":[{"text":"any function that makes use of scientific or mathematical constants, often represented by Greek letters in academic writing","correct":false},{"text":"a function that get executed when decorators are used","correct":false},{"text":"any function whose definition is contained within five lines of code or fewer","correct":false},{"text":"a small, anonymous function that can take any number of arguments but has only expression to evaluate","correct":true}],"illustrator":""},{"question":". What is the primary difference between lists and tuples?","options":[{"text":"You can access a specific element in a list by indexing to its position, but you cannot access a specific element in a tuple unless you iterate through the tuple","correct":false},{"text":"Lists are mutable, meaning you can change the data that is inside them at any time. Tuples are immutable, meaning you cannot change the data that is inside them once you have created the tuple.","correct":true},{"text":"Lists are immutable, meaning you cannot change the data that is inside them once you have created the list. Tuples are mutable, meaning you can change the data that is inside them at any time.","correct":false},{"text":"Lists can hold several data types inside them at once, but tuples can only hold the same data type if multiple elements are present.","correct":false}],"illustrator":""},{"question":". What does a generator return?","options":[{"text":"None","correct":false},{"text":"An iterable object","correct":true},{"text":"A linked list data structure from a non-empty list","correct":false},{"text":"All the keys of the given dictionary","correct":false}],"illustrator":""},{"question":". What is the difference between class attributes and instance attributes?","options":[{"text":"Instance attributes can be changed, but class attributes cannot be changed","correct":false},{"text":"Class attributes are shared by all instances of the class. Instance attributes may be unique to just that instance","correct":true},{"text":"There is no difference between class attributes and instance attributes","correct":false},{"text":"Class attributes belong just to the class, not to instance of that class. Instance attributes are shared among all instances of a class","correct":false}],"illustrator":""},{"question":". What is the correct syntax of creating an instance method?","options":[{"text":"<br>","correct":false},{"text":"<br>","correct":true},{"text":"<br>","correct":false},{"text":"<br>","correct":false}],"illustrator":"```python\ndef self.get_next_card(self):\n  # method body goes here\n```"},{"question":". What is the correct way to call a function?","options":[{"text":"`get_max_num([57, 99, 31, 18])`","correct":true},{"text":"`call.(get_max_num)`","correct":false},{"text":"`def get_max_num([57, 99, 31, 18])`","correct":false},{"text":"`call.get_max_num([57, 99, 31, 18])`","correct":false}],"illustrator":""},{"question":". How is comment created?","options":[{"text":"`-- This is a comment`","correct":false},{"text":"`# This is a comment`","correct":true},{"text":"`/_ This is a comment _\\`","correct":false},{"text":"`// This is a comment`","correct":false}],"illustrator":""},{"question":". What is the correct syntax for replacing the string apple in the list with the string orange?","options":[{"text":"`orange = my_list[1]`","correct":false},{"text":"`my_list[1] = 'orange'`","correct":true},{"text":"`my_list['orange'] = 1`","correct":false},{"text":"`my_list[1] == orange`","correct":false}],"illustrator":"```python\nmy_list = ['kiwi', 'apple', 'banana']\n```"},{"question":". What will happen if you use a while loop and forget to include logic that eventually causes the while loop to stop?","options":[{"text":"Nothing will happen; your computer knows when to stop running the code in the while loop.","correct":false},{"text":"You will get a KeyError.","correct":false},{"text":"Your code will get stuck in an infinite loop.","correct":true},{"text":"You will get a WhileLoopError.","correct":false}],"illustrator":""},{"question":". Describe the functionality of a queue?","options":[{"text":"A queue adds items to either end and removes items from either end.","correct":true},{"text":"A queue adds items to the top and removes items from the top.","correct":false},{"text":"A queue adds items to the top, and removes items from anywhere in, a list.","correct":false},{"text":"A queue adds items to the top and removes items from anywhere in the queue.","correct":false}],"illustrator":""},{"question":". Which choice is the most syntactically correct example of the conditional branching?","options":[{"text":"<br>","correct":true},{"text":"<br>","correct":false},{"text":"<br>","correct":false},{"text":"<br>","correct":false}],"illustrator":"```python\nif num_people > 10;\n    print(\"There is a lot of people in the pool.\")\nif num_people > 4;\n    print(\"There are some people in the pool.\")\nelse;\n    print(\"There is no one in the pool.\")\n```"},{"question":". How does `defaultdict` work?","options":[{"text":"`defaultdict` will automatically create a dictionary for you that has keys which are the integers 0-10.","correct":false},{"text":"`defaultdict` forces a dictionary to only accept keys that are of the types specified when you created the `defaultdict` (such as strings or integers).","correct":false},{"text":"If you try to read from a `defaultdict` with a nonexistent key, a new default key-value pair will be created for you instead of throwing a `KeyError`.","correct":true},{"text":"`defaultdict` stores a copy of a dictionary in memory that you can default to if the original gets unintentionally modified.","correct":false}],"illustrator":""},{"question":". What is the correct syntax for adding a key called `variety` to the `fruit_info` dictionary that has a value of `Red Delicious`?","options":[{"text":"`fruit_info['variety'] == 'Red Delicious'`","correct":false},{"text":"`fruit_info['variety'] = 'Red Delicious'`","correct":true},{"text":"`red_delicious = fruit_info['variety']`","correct":false},{"text":"`red_delicious == fruit_info['variety']`","correct":false}],"illustrator":""},{"question":". When would you use a `while` loop?","options":[{"text":"when you want to minimize the use of strings in your code","correct":false},{"text":"when you want to run code in one file while code in another file is also running","correct":false},{"text":"when you want some code to continue running as long as some condition is true","correct":true},{"text":"when you need to run two or more chunks of code at once within the same file","correct":false}],"illustrator":"```python\ni = 1\nwhile i<6:\n    print('Countdown:',i)\n    i = i + 1\n```"},{"question":". What is the correct syntax for defining an `__init__()` method that sets instance-specific attributes upon creation of a new class instance?","options":[{"text":"<br>","correct":false},{"text":"<br>","correct":false},{"text":"<br>","correct":true},{"text":"<br>","correct":false}],"illustrator":"```python\ndef __init__(attr1, attr2):\n    self.attr1 = attr1\n    self.attr2 = attr2\n```"},{"question":". What would this recursive function print if it is called with no parameters?","options":[{"text":"<br>","correct":false},{"text":"<br>","correct":false},{"text":"<br>","correct":false},{"text":"<br>","correct":true}],"illustrator":"```python\n1\n2\n3\n```"},{"question":". In Python, when using sets, you use **\\_** to calculate the intersection between two sets and **\\_** to calculate the union.","options":[{"text":"`Intersect`; `union`","correct":false},{"text":"`|`; `&`","correct":false},{"text":"`&`; `|`","correct":true},{"text":"`&&`; `||`","correct":false}],"illustrator":""},{"question":". What will this code fragment return?","options":[{"text":"It returns a 5x5 matric; each row will have the values 1,2,3,4,5.","correct":false},{"text":"It returns an array with the values 1,2,3,4,5","correct":false},{"text":"It returns five different square matrices filled with ones. The first is 1x1, the second 2x2, and so on to 5x5","correct":false},{"text":"It returns a 5-dimensional array of size 1x2x3x4x5 filled with 1s.","correct":true}],"illustrator":"```python\nimport numpy as np\nnp.ones([1,2,3,4,5])\n```"},{"question":". You encounter a FileNotFoundException while using just the filename in the `open` function. What might be the easiest solution?","options":[{"text":"Make sure the file is on the system PATH","correct":false},{"text":"Create a symbolic link to allow better access to the file","correct":false},{"text":"Copy the file to the same directory as where the script is running from","correct":true},{"text":"Add the path to the file to the PYTHONPATH environment variable","correct":false}],"illustrator":""},{"question":". what will this command return?","options":[{"text":"a set of all the multiples of 3 less then 100","correct":true},{"text":"a set of all the number from 0 to 100 multiplied by 3","correct":false},{"text":"a list of all the multiples of 3 less then 100","correct":false},{"text":"a set of all the multiples of 3 less then 100 excluding 0","correct":false}],"illustrator":"```python\n{x for x in range(100) if x%3 == 0}\n```"},{"question":". What does the // operator in Python 3 allow you to do?","options":[{"text":"Perform integer division","correct":true},{"text":"Perform operations on exponents","correct":false},{"text":"Find the remainder of a division operation","correct":false},{"text":"Perform floating point division","correct":false}],"illustrator":""},{"question":". What file is imported to use dates in python?","options":[{"text":"datetime","correct":true},{"text":"dateday","correct":false},{"text":"daytime","correct":false},{"text":"timedate","correct":false}],"illustrator":""},{"question":". What is the correct syntax for defining a class called Game?","options":[{"text":"`def Game(): pass`","correct":false},{"text":"`def Game: pass`","correct":false},{"text":"`class Game: pass`","correct":true},{"text":"`class Game(): pass`","correct":false}],"illustrator":""},{"question":". What is the correct syntax for calling an instance method on a class named Game?","options":[{"text":"`my_game = Game(self) self.my_game.roll_dice()`","correct":false},{"text":"`my_game = Game() self.my_game.roll_dice()`","correct":false},{"text":"`my_game = Game() my_game.roll_dice()`","correct":true},{"text":"`my_game = Game(self) my_game.roll_dice(self)`","correct":false}],"illustrator":""},{"question":". What is the output of this code? (NumPy has been imported as np.)?","options":[{"text":"`{0,2}`","correct":false},{"text":"`[2]`","correct":true},{"text":"`{2}`","correct":false},{"text":"`[0,2,0,0]`","correct":false}],"illustrator":"```python\na = np.array([1,2,3,4])\nprint(a[[False, True, False, False]])\n```"},{"question":". Suppose you have a string variable defined as y=”stuff;thing;junk;”. What would be the output from this code?","options":[{"text":"17","correct":false},{"text":"4","correct":true},{"text":"0","correct":false},{"text":"3","correct":false}],"illustrator":"```\ny=”stuff;thing;junk”\n\tlen(z) ==> 3\ny=”stuff;thing;junk;”\n\tlen(z) ==> 4\n```"},{"question":". What is the output of this code?","options":[{"text":"`[1,2,4,5]`","correct":false},{"text":"`[1,3,4,5]`","correct":true},{"text":"`[3,4,5]`","correct":false},{"text":"`[1,2,3]`","correct":false}],"illustrator":"```python\nnum_list = [1,2,3,4,5]\nnum_list.pop(3)\n>>> [1,2,4,5]\nnum_list.remove(2)\n>>> [1,3,4,5]\n```"},{"question":". Which command will create a list from 10 down to 1? Example:","options":[{"text":"`reversed(list(range(1,11)))`","correct":false},{"text":"`list(reversed(range(1,10)))`","correct":false},{"text":"`list(range(10,1,-1))`","correct":false},{"text":"`list(reversed(range(1,11)))`","correct":true}],"illustrator":""},{"question":". Which fragment of code will print exactly the same output as this fragment?","options":[{"text":"<br>","correct":false},{"text":"<br>","correct":true},{"text":"<br>","correct":false},{"text":"<br>","correct":false}],"illustrator":"```python\ny = 1\nfor i in range(1,10):\n    y = y * 2\nprint(y)\n```"},{"question":". Elements surrounded by `[]` are **\\_**, `{}` are **\\_**, and `()` are **\\_**.","options":[{"text":"sets only; lists or dictionaries; tuples","correct":false},{"text":"lists; sets only; tuples","correct":false},{"text":"tuples; sets or lists; dictionaries","correct":false},{"text":"lists; dictionaries or sets; tuples","correct":true}],"illustrator":""},{"question":". What is the output of this code? (NumPy has been imported as np.)","options":[{"text":"`[2, 4]`","correct":false},{"text":"`[3, 4]`","correct":true},{"text":"`[4]`","correct":false},{"text":"`[1,2]`","correct":false}],"illustrator":"```python\ntable = np.array([\n    [1,3],\n    [2,4]])\nprint(table.max(axis=1))\n```"},{"question":". What will this code print?","options":[{"text":"`The number is 3`","correct":true},{"text":"`the number is 3`","correct":false},{"text":"`THE NUMBER IS 3`","correct":false},{"text":"It throws a TypeError because the integer must be cast to a string.","correct":false}],"illustrator":"```python\nnumber = 3\nprint (f\"The number is {number}\")\n```"},{"question":". Which syntax correctly creates a variable that is bound to a tuple?","options":[{"text":"`my_tuple tup(2, 'apple', 3.5) %D`","correct":false},{"text":"`my_tuple [2, 'apple', 3.5].tuple() %D`","correct":false},{"text":"`my_tuple = (2, 'apple', 3.5)`","correct":true},{"text":"`my_tuple = [2, 'apple', 3.5]`","correct":false}],"illustrator":""},{"question":"0. Which mode is not a valid way to access a file from within a Python script?","options":[{"text":"`write('w')`","correct":false},{"text":"`scan('s')`","correct":true},{"text":"`append('a')`","correct":false},{"text":"`read('r')`","correct":false}],"illustrator":""},{"question":"1. NumPy allows you to multiply two arrays without a for loop. This is an example of \\_.","options":[{"text":"vectorization","correct":true},{"text":"attributions","correct":false},{"text":"accelaration","correct":false},{"text":"functional programming","correct":false}],"illustrator":""},{"question":"2. What built-in Python data type can be used as a hash table?","options":[{"text":"`set`","correct":false},{"text":"`list`","correct":false},{"text":"`tuple`","correct":false},{"text":"`dictionary`","correct":true}],"illustrator":""},{"question":"3. Which Python function allows you to execute Linux shell commands in Python?","options":[{"text":"`sys.exc_info()`","correct":false},{"text":"`os.system()`","correct":true},{"text":"`os.getcwd()`","correct":false},{"text":"`sys.executable`","correct":false}],"illustrator":""},{"question":"4. Suppose you have the following code snippet and want to extract a list with only the letters. Which fragment of code will \\_not\\_ achieve that goal?","options":[{"text":"<br>","correct":true},{"text":"`letters = my_dictionary.keys()`","correct":false},{"text":"`letters = [letter for (letter, number) in my_dictionary.items()]`","correct":false},{"text":"`letters4 = list(my_dictionary)`","correct":false}],"illustrator":"```python\nletters = []\nfor letter in my_dictionary.values():\n    letters.append(letter)\n```"},{"question":"5. When an array is large, NumPy will not print the entire array when given the built-in `print` function. What function can you use within NumPy to force it to print the entire array?","options":[{"text":"`set_printparams`","correct":false},{"text":"`set_printoptions`","correct":true},{"text":"`set_fullprint`","correct":false},{"text":"`setp_printwhole`","correct":false}],"illustrator":""},{"question":"6. When would you use a try/except block in code?","options":[{"text":"You use `try/except` blocks when you want to run some code, but need a way to execute different code if an exception is raised.","correct":true},{"text":"You use `try/except` blocks inside of unit tests so that the unit testes will always pass.","correct":false},{"text":"You use `try/except` blocks so that you can demonstrate to your code reviewers that you tried a new approach, but if the new approach is not what they were looking for, they can leave comments under the `except` keyword.","correct":false},{"text":"You use `try/except` blocks so that none of your functions or methods return `None`.","correct":false}],"illustrator":""},{"question":"7. In Python, how can the compiler identify the inner block of a for loop?","options":[{"text":"`because of the level of indentation after the for loop`","correct":true},{"text":"`because of the end keyword at the end of the for loop`","correct":false},{"text":"`because of the block is surrounded by brackets ({})`","correct":false},{"text":"`because of the blank space at the end of the body of the for loop`","correct":false}],"illustrator":""},{"question":"8. What Python mechanism is best suited for telling a user they are using a deprecated function","options":[{"text":"sys.stdout","correct":false},{"text":"traceback","correct":false},{"text":"warnings","correct":true},{"text":"exceptions","correct":false}],"illustrator":""},{"question":"9. What will be the value of x after running this code?","options":[{"text":"`{1, 2, 3, 4, 5, 5, 6}`","correct":false},{"text":"`{5, 6, 1, 2, 3, 4, 5, 6}`","correct":false},{"text":"`{6, 1, 2, 3, 4, 5}`","correct":false},{"text":"`{1, 2, 3, 4, 5, 6}`","correct":true}],"illustrator":"```python\nx = {1,2,3,4,5}\nx.add(5)\nx.add(6)\n```"},{"question":"0. How would you access and store all of the keys in this dictionary at once?","options":[{"text":"`my_keys = fruit_info.to_keys()`","correct":false},{"text":"`my_keys = fruit_info.all_keys()`","correct":false},{"text":"`my_keys = fruit_info.keys`","correct":false},{"text":"`my_keys = fruit_info.keys()`","correct":true}],"illustrator":"```python\nfruit_info = {\n    'fruit': 'apple',\n    'count': 2,\n    'price': 3.5\n}\n```"},{"question":"1. What is wrong with this function definition?","options":[{"text":"`name` is a reserved word.","correct":false},{"text":"Underscores are not allowed in function names.","correct":false},{"text":"A non-default argument follows a default argument.","correct":true},{"text":"There is nothing wrong with this function definition.","correct":false}],"illustrator":"```python\ndef be_friendly(greet = \"How are you!\", name):\n    pass\n```"},{"question":"2. Given that NumPy is imported as `np`, which choice will return `True`?","options":[{"text":"<br>","correct":true},{"text":"<br>","correct":false},{"text":"<br>","correct":false},{"text":"<br>","correct":false}],"illustrator":"```python\na = np.array([1, np.nan])\nnp.array_equal(a,a)\n```"},{"question":"3. How do you add a comment to existing Python script?","options":[{"text":"`// This is a comment`","correct":false},{"text":"`# This is a comment`","correct":true},{"text":"`-- This is a comment`","correct":false},{"text":"`/* This is a comment *\\`","correct":false}],"illustrator":""},{"question":"4. In this code fragment, what will the values of c and d be equivalent to?","options":[{"text":"A","correct":false},{"text":"B","correct":false},{"text":"C","correct":false},{"text":"D","correct":true}],"illustrator":"```python\nc = [ a[0] * b[0], a[1] * b[1], a[2] * b[2] ]\nd = sum(c)\n```"},{"question":"5. What two functions within the NumPy library could you use to solve a system of linear equations?","options":[{"text":"`linalg.eig() and .matmul()`","correct":true},{"text":"`linalg.inv() and .dot()`","correct":false},{"text":"`linalg.det() and .dot()`","correct":false},{"text":"`linalg.inv() and .eye()`","correct":false}],"illustrator":""},{"question":"6. What is the correct syntax for creating a vaiable that is bound to a list?","options":[{"text":"`my_list = (2, 'apple', 3.5)`","correct":false},{"text":"`my_list = [2, 'apple', 3.5]`","correct":true},{"text":"`my_list = [2, 'apple', 3.5].to_list()`","correct":false},{"text":"`my_list = to_list(2, 'apple', 3.5)`","correct":false}],"illustrator":""},{"question":"7. This code provides the **\\_** of the list of numbers.","options":[{"text":"mode","correct":false},{"text":"average","correct":false},{"text":"mean","correct":false},{"text":"median","correct":true}],"illustrator":"```python\nnum_list = [21, 13, 19, 3, 11, 5, 18]\nnum_list.sort()\nnum_list[len(num_list) // 2]\n```"},{"question":"8. What are the two main data structures in the Pandas library?","options":[{"text":"Arrays and DataFrames","correct":false},{"text":"Series and Matrixes","correct":false},{"text":"Matrixes and DataFrames","correct":false},{"text":"Series and DataFrames","correct":true}],"illustrator":""},{"question":"9. Suppose you have a variale named `vector` of type np.array with 10,000 elements. How can you turn `vector` into a variable named `matrix` with dimensions 100x100?","options":[{"text":"`matrix = (vector.shape = (100,100))`","correct":false},{"text":"`matrix = vector.to_matrix(100,100)`","correct":false},{"text":"`matrix = matrix(vector,100,100)`","correct":false},{"text":"`matrix = vector.reshape(100, 100)`","correct":true}],"illustrator":""},{"question":"0. Which choice is an immutable data type?","options":[{"text":"dictionnary","correct":false},{"text":"list","correct":false},{"text":"set","correct":false},{"text":"string","correct":true}],"illustrator":""},{"question":"1. What is the output of this code?","options":[{"text":"<br>","correct":false},{"text":"<br>","correct":false},{"text":"<br>","correct":true},{"text":"<br>","correct":false}],"illustrator":"```\nHello, I am from Spain\nHello, I am from France\nHello, I am from France\n```"},{"question":"2. Choose the option below for which instance of the class cannot be created","options":[{"text":"Anonymous Class","correct":false},{"text":"Parent Class","correct":false},{"text":"Nested Class","correct":false},{"text":"Abstract Class","correct":true}],"illustrator":""},{"question":"3. Using Pandas, we load a data set from Kaggle, as structured in the image below. Which command will return the total number of survivors?","options":[{"text":"`sum(titanic['Survived'])`","correct":true},{"text":"`[x for x in titanic['Survived'] if x == 1]`","correct":false},{"text":"`len(titanic[\"Survived\"])`","correct":false},{"text":"`sum(titanic['Survived']==0)`","correct":false}],"illustrator":""},{"question":"4. How would you create a list of tuples matching these lists of characters and actors?","options":[{"text":"`[(x,y)] for x in characters for y in actors]`","correct":false},{"text":"`list(zip(characters, actors))`","correct":true},{"text":"<br>","correct":false},{"text":"`{x:y for x in characters for y in actors}`","correct":false}],"illustrator":"```python\nd = {}\nfor x in range(1, len(characters)):\n    d[x] = actors[x]\n```"},{"question":"5. What will this statement return?","options":[{"text":"a dictionary with x as a key, and x squared as its value; from 1 to 100","correct":false},{"text":"a dictionary with x as a key, and x squared as its value; from 1 to 99","correct":true},{"text":"a set of tuples, consisting of (x, x squared); from 1 to 99","correct":false},{"text":"a list with all numbers squared from 1 to 99","correct":false}],"illustrator":"```python\n{x : x*x for x in range(1,100)}\n```"},{"question":"6. Jaccard Similarity is a formula that tells you how similar two sets are. It is defined as the cardinality of the intersection divided by the cardinality of the union. Which choice is an accurate implementation in Python?","options":[{"text":"`def jaccard(a, b): return len (a | b) / len (a & b)`","correct":false},{"text":"`def jaccard(a, b): return len (a & b) / len (a | b)`","correct":true},{"text":"`def jaccard(a, b): return len (a && b) / len (a || b)`","correct":false},{"text":"`def jaccard(a, b): return a.intersection(b) / a.union(b)`","correct":false}],"illustrator":""},{"question":"7. Which choice is not a native numerical type in Python?","options":[{"text":"Long","correct":false},{"text":"Int","correct":false},{"text":"Float","correct":false},{"text":"Double","correct":true}],"illustrator":""},{"question":"8. What will be the output of this code?","options":[{"text":"`[3,2,3]`","correct":false},{"text":"`[1, 2, 3, 1, 2, 3, 1, 2, 3]`","correct":true},{"text":"You will get a type error.","correct":false},{"text":"`[3,6,9]`","correct":false}],"illustrator":"```python\n[1,2,3] * 3\n```"},{"question":"9. Given a list defined as numbers = `[1,2,3,4]`, what is the value of `numbers[-2]`?","options":[{"text":"1","correct":false},{"text":"3","correct":true},{"text":"2","correct":false},{"text":"An IndexError exception is thrown.","correct":false}],"illustrator":""},{"question":"0. Which statement about strings in Python is true?","options":[{"text":"Strings can be enclosed by double quotes (\") or single quotes (').","correct":true},{"text":"Strings can only be enclosed in single quotes (').","correct":false},{"text":"Single character strings must be enclosed in single quotes ('), and the rest must be enclosed in double quotes (\").","correct":false},{"text":"Strings can only be enclosed in double quotes (\").","correct":false}],"illustrator":""},{"question":"1. What is the correct syntax for defining an _init_() method that takes no parameters?","options":[{"text":"def*init*(self): pass","correct":false},{"text":"class*init*(self): pass","correct":false},{"text":"class*init*(): pass","correct":false},{"text":"def*init*(): pass","correct":true}],"illustrator":""}]